{
	"$schema": "https://biomejs.dev/schemas/2.3.11/schema.json",
	"vcs": {
		"enabled": true,
		"clientKind": "git",
		"useIgnoreFile": true
	},
	"files": {
		"ignoreUnknown": false
	},
	"formatter": {
		"enabled": true,
		"indentStyle": "tab",
		"indentWidth": 2,
		"lineWidth": 100
	},
	"linter": {
		"enabled": true,
		"rules": {
			"recommended": true,
			"a11y": {
				"useKeyWithClickEvents": "warn",
				"noSvgWithoutTitle": "warn"
			},
			"complexity": {
				"noExcessiveCognitiveComplexity": "warn"
			},
			"correctness": {
				"useExhaustiveDependencies": "warn",
				"noUnusedVariables": "error"
			},
			"style": {
				"noNonNullAssertion": "off",
				"useImportType": "error"
			},
			"suspicious": {
				"noArrayIndexKey": "warn",
				"noExplicitAny": "warn"
			}
		}
	},
	"javascript": {
		"formatter": {
			"quoteStyle": "double",
			"semicolons": "asNeeded",
			"trailingCommas": "es5",
			"arrowParentheses": "always"
		}
	},
	"css": {
		"parser": {
			"tailwindDirectives": true
		},
		"linter": {
			"enabled": true
		}
	},
	"overrides": [
		{
			"includes": ["*.test.ts", "*.test.tsx", "*.spec.ts", "*.spec.tsx", "*.stories.tsx"],
			"linter": {
				"rules": {
					"suspicious": {
						"noExplicitAny": "off"
					}
				}
			}
		}
	],
	"assist": {
		"enabled": true,
		"actions": {
			"source": {
				"organizeImports": "on"
			}
		}
	}
}
